TheBigBangTheory/__init__.py
TheBigBangTheory/_version.py
TheBigBangTheory/data/Season1.dev.lst
TheBigBangTheory/data/Season1.trn.lst
TheBigBangTheory/data/Season1.tst.lst
TheBigBangTheory/data/forced_alignment/TheBigBangTheory.Season01.Episode01.out
TheBigBangTheory/data/forced_alignment/TheBigBangTheory.Season01.Episode02.out
TheBigBangTheory/data/forced_alignment/TheBigBangTheory.Season01.Episode03.out
TheBigBangTheory/data/forced_alignment/TheBigBangTheory.Season01.Episode04.out
TheBigBangTheory/data/forced_alignment/TheBigBangTheory.Season01.Episode05.out
TheBigBangTheory/data/forced_alignment/TheBigBangTheory.Season01.Episode06.out
TheBigBangTheory/data/forced_alignment/TheBigBangTheory.Season01.Episode07.out
TheBigBangTheory/data/forced_alignment/TheBigBangTheory.Season01.Episode08.out
TheBigBangTheory/data/forced_alignment/TheBigBangTheory.Season01.Episode09.out
TheBigBangTheory/data/forced_alignment/TheBigBangTheory.Season01.Episode10.out
TheBigBangTheory/data/forced_alignment/TheBigBangTheory.Season01.Episode11.out
TheBigBangTheory/data/forced_alignment/TheBigBangTheory.Season01.Episode12.out
TheBigBangTheory/data/forced_alignment/TheBigBangTheory.Season01.Episode13.out
TheBigBangTheory/data/forced_alignment/TheBigBangTheory.Season01.Episode14.out
TheBigBangTheory/data/forced_alignment/TheBigBangTheory.Season01.Episode15.out
TheBigBangTheory/data/forced_alignment/TheBigBangTheory.Season01.Episode16.out
TheBigBangTheory/data/forced_alignment/TheBigBangTheory.Season01.Episode17.out
TheBigBangTheory/data/forced_alignment/TheBigBangTheory.Season02.Episode01.out
TheBigBangTheory/data/forced_alignment/TheBigBangTheory.Season02.Episode02.out
TheBigBangTheory/data/forced_alignment/TheBigBangTheory.Season02.Episode03.out
TheBigBangTheory/data/forced_alignment/TheBigBangTheory.Season02.Episode04.out
TheBigBangTheory/data/forced_alignment/TheBigBangTheory.Season02.Episode05.out
pyannote.db.thebigbangtheory-0.1.1.dist-info/DESCRIPTION.rst
pyannote.db.thebigbangtheory-0.1.1.dist-info/METADATA
pyannote.db.thebigbangtheory-0.1.1.dist-info/RECORD
pyannote.db.thebigbangtheory-0.1.1.dist-info/WHEEL
pyannote.db.thebigbangtheory-0.1.1.dist-info/entry_points.txt
pyannote.db.thebigbangtheory-0.1.1.dist-info/metadata.json
pyannote.db.thebigbangtheory-0.1.1.dist-info/top_level.txt
