Metadata-Version: 2.0
Name: pyannote.db.thebigbangtheory
Version: 0.1.1
Summary: TheBigBangTheory plugin for pyannote-database
Home-page: UNKNOWN
Author: Hervé Bredin
Author-email: bredin@limsi.fr
License: UNKNOWN
Platform: UNKNOWN
Classifier: Development Status :: 4 - Beta
Classifier: Intended Audience :: Science/Research
Classifier: License :: OSI Approved :: MIT License
Classifier: Natural Language :: English
Classifier: Programming Language :: Python :: 2
Classifier: Programming Language :: Python :: 2.7
Classifier: Programming Language :: Python :: 3
Classifier: Programming Language :: Python :: 3.5
Classifier: Programming Language :: Python :: 3.6
Classifier: Topic :: Scientific/Engineering
Requires-Dist: pandas (>=0.17.1)
Requires-Dist: pyannote.core (>=1.0)
Requires-Dist: pyannote.database (>=0.12)
